{"municipality":"14363","name":"足柄上郡松田町","prefecture":"神奈川県","source":{"dataset":"frogcat/japan-small-area","census":"平成27年国勢調査 小地域（e-Stat 統計LOD）","license":"MIT（リポジトリ）／政府統計の総合窓口(e-Stat)の利用規約（元データ・出典表記必要）","fetched":"2026-07-06"},"towns":[{"code":"14363001000","name":"松田庶子","lat":35.359466,"lng":139.128653},{"code":"14363001001","name":"松田庶子","lat":35.34284,"lng":139.141312},{"code":"14363002001","name":"松田惣領","lat":35.356345,"lng":139.144999},{"code":"14363002002","name":"松田惣領","lat":35.341575,"lng":139.14298},{"code":"143630030","name":"神山","lat":35.349603,"lng":139.155961},{"code":"143630040","name":"寄","lat":35.406566,"lng":139.127281}]}
