{"municipality":"23427","name":"海部郡飛島村","prefecture":"愛知県","source":{"dataset":"frogcat/japan-small-area","census":"平成27年国勢調査 小地域（e-Stat 統計LOD）","license":"MIT（リポジトリ）／政府統計の総合窓口(e-Stat)の利用規約（元データ・出典表記必要）","fetched":"2026-07-06"},"towns":[{"code":"234270010","name":"大字服岡","lat":35.090634,"lng":136.788745},{"code":"234270020","name":"大字三福","lat":35.091199,"lng":136.804749},{"code":"234270030","name":"大字渚","lat":35.085993,"lng":136.801848},{"code":"234270041","name":"大宝","lat":35.089755,"lng":136.771117},{"code":"234270042","name":"大字重宝","lat":35.083042,"lng":136.771508},{"code":"234270050","name":"大字松之郷","lat":35.082052,"lng":136.797447},{"code":"234270060","name":"元起","lat":35.081022,"lng":136.781414},{"code":"234270070","name":"大字飛島新田","lat":35.076909,"lng":136.799225},{"code":"234270080","name":"大字梅之郷","lat":35.078338,"lng":136.816601},{"code":"234270090","name":"大字古政成","lat":35.073363,"lng":136.789552},{"code":"234270100","name":"大字新政成","lat":35.068305,"lng":136.806076},{"code":"234270110","name":"木場","lat":35.045843,"lng":136.821615}]}
