{"municipality":"47303","name":"国頭郡東村","prefecture":"沖縄県","source":{"dataset":"frogcat/japan-small-area","census":"平成27年国勢調査 小地域（e-Stat 統計LOD）","license":"MIT（リポジトリ）／政府統計の総合窓口(e-Stat)の利用規約（元データ・出典表記必要）","fetched":"2026-07-06"},"towns":[{"code":"473030010","name":"字平良","lat":26.633037,"lng":128.141303},{"code":"473030020","name":"字慶佐次","lat":26.614454,"lng":128.13092},{"code":"473030030","name":"字有銘","lat":26.605899,"lng":128.113923},{"code":"473030040","name":"字高江","lat":26.670585,"lng":128.23079},{"code":"473030050","name":"字宮城","lat":26.64384,"lng":128.203346},{"code":"473030060","name":"字川田","lat":26.652538,"lng":128.1807}]}
