{"municipality":"13218","name":"福生市","prefecture":"東京都","source":{"dataset":"frogcat/japan-small-area","census":"平成27年国勢調査 小地域（e-Stat 統計LOD）","license":"MIT（リポジトリ）／政府統計の総合窓口(e-Stat)の利用規約（元データ・出典表記必要）","fetched":"2026-07-06"},"towns":[{"code":"13218001090","name":"大字熊川","lat":35.728688,"lng":139.33817},{"code":"13218001091","name":"大字熊川","lat":35.720346,"lng":139.338583},{"code":"13218001092","name":"大字熊川","lat":35.722839,"lng":139.342464},{"code":"13218002090","name":"大字福生","lat":35.742656,"lng":139.326208},{"code":"13218002091","name":"大字福生","lat":35.741105,"lng":139.329127},{"code":"132180030","name":"牛浜","lat":35.73447,"lng":139.33311},{"code":"132180040","name":"志茂","lat":35.736811,"lng":139.329809},{"code":"132180050","name":"本町","lat":35.740046,"lng":139.327954},{"code":"13218006000","name":"北田園","lat":35.736053,"lng":139.319719},{"code":"13218006001","name":"北田園１丁目","lat":35.73271,"lng":139.325203},{"code":"13218006002","name":"北田園２丁目","lat":35.736151,"lng":139.321874},{"code":"13218007000","name":"南田園","lat":35.726635,"lng":139.328175},{"code":"13218007001","name":"南田園１丁目","lat":35.722188,"lng":139.331518},{"code":"13218007002","name":"南田園２丁目","lat":35.726191,"lng":139.331317},{"code":"13218007003","name":"南田園３丁目","lat":35.729994,"lng":139.329322},{"code":"13218008001","name":"武蔵野台１丁目","lat":35.748497,"lng":139.332932},{"code":"13218008002","name":"武蔵野台２丁目","lat":35.74885,"lng":139.329832},{"code":"13218009001","name":"加美平１丁目","lat":35.749777,"lng":139.326211},{"code":"13218009002","name":"加美平２丁目","lat":35.749118,"lng":139.323859},{"code":"13218009003","name":"加美平３丁目","lat":35.74801,"lng":139.321749},{"code":"13218009004","name":"加美平４丁目","lat":35.753188,"lng":139.324899},{"code":"132180100","name":"東町","lat":35.743631,"lng":139.327573},{"code":"132180110","name":"横田基地内","lat":35.73823,"lng":139.346637},{"code":"132180120","name":"大字熊川二宮","lat":35.733253,"lng":139.338893},{"code":"132180130","name":"大字福生二宮","lat":35.735075,"lng":139.339614}]}
