{"municipality":"20304","name":"南佐久郡川上村","prefecture":"長野県","source":{"dataset":"frogcat/japan-small-area","census":"平成27年国勢調査 小地域（e-Stat 統計LOD）","license":"MIT（リポジトリ）／政府統計の総合窓口(e-Stat)の利用規約（元データ・出典表記必要）","fetched":"2026-07-06"},"towns":[{"code":"203040010","name":"大字樋沢","lat":35.96778,"lng":138.503823},{"code":"203040020","name":"大字御所平","lat":35.949292,"lng":138.522648},{"code":"203040030","name":"大字原","lat":35.943105,"lng":138.56141},{"code":"203040040","name":"大字大深山","lat":35.98003,"lng":138.578198},{"code":"203040050","name":"大字居倉","lat":35.953864,"lng":138.608144},{"code":"203040060","name":"大字秋山","lat":35.936369,"lng":138.677848},{"code":"203040070","name":"大字梓山","lat":35.956604,"lng":138.700607},{"code":"203040080","name":"大字川端下","lat":35.907112,"lng":138.640064}]}
