{"municipality":"24562","name":"南牟婁郡紀宝町","prefecture":"三重県","source":{"dataset":"frogcat/japan-small-area","census":"平成27年国勢調査 小地域（e-Stat 統計LOD）","license":"MIT（リポジトリ）／政府統計の総合窓口(e-Stat)の利用規約（元データ・出典表記必要）","fetched":"2026-07-06"},"towns":[{"code":"245620010","name":"桐原","lat":33.793644,"lng":135.970579},{"code":"245620020","name":"高岡","lat":33.757675,"lng":135.954472},{"code":"245620030","name":"井田","lat":33.760315,"lng":136.013804},{"code":"245620040","name":"鵜殿","lat":33.737214,"lng":136.011664}]}
