{"municipality":"39411","name":"高岡郡津野町","prefecture":"高知県","source":{"dataset":"frogcat/japan-small-area","census":"平成27年国勢調査 小地域（e-Stat 統計LOD）","license":"MIT（リポジトリ）／政府統計の総合窓口(e-Stat)の利用規約（元データ・出典表記必要）","fetched":"2026-07-06"},"towns":[{"code":"394110010","name":"新土居","lat":33.43613,"lng":133.23799},{"code":"394110020","name":"三間川","lat":33.448134,"lng":133.242878},{"code":"394110030","name":"樺ノ川","lat":33.452346,"lng":133.232225},{"code":"394110040","name":"西谷","lat":33.450877,"lng":133.225141},{"code":"394110050","name":"姫野々","lat":33.437059,"lng":133.214351},{"code":"394110060","name":"久保川","lat":33.454731,"lng":133.213627},{"code":"394110070","name":"永野","lat":33.44196,"lng":133.20045},{"code":"394110080","name":"貝ノ川","lat":33.461759,"lng":133.19871},{"code":"394110090","name":"西谷乙","lat":33.427774,"lng":133.196975},{"code":"394110100","name":"貝ノ川床鍋","lat":33.41032,"lng":133.188418},{"code":"394110110","name":"赤木","lat":33.456719,"lng":133.182748},{"code":"394110120","name":"大野","lat":33.442088,"lng":133.169913},{"code":"394110130","name":"黒川","lat":33.453616,"lng":133.157055},{"code":"394110150","name":"杉ノ川甲","lat":33.447047,"lng":133.144245},{"code":"394110160","name":"杉ノ川乙","lat":33.428529,"lng":133.159849},{"code":"394110170","name":"杉ノ川丙","lat":33.452815,"lng":133.168881},{"code":"394110180","name":"白石甲","lat":33.441453,"lng":133.120828},{"code":"394110190","name":"白石乙","lat":33.427107,"lng":133.124534},{"code":"394110200","name":"白石丙","lat":33.439918,"lng":133.186234},{"code":"394110210","name":"北川","lat":33.381373,"lng":133.009291},{"code":"394110220","name":"芳生野甲","lat":33.414837,"lng":133.025449},{"code":"394110230","name":"力石","lat":33.404515,"lng":133.042551},{"code":"394110240","name":"烏出川","lat":33.40352,"lng":133.059984},{"code":"394110250","name":"船戸","lat":33.430526,"lng":133.085356},{"code":"394110260","name":"桑ケ市","lat":33.396365,"lng":133.090281},{"code":"394110270","name":"芳生野乙","lat":33.445529,"lng":133.004804},{"code":"394110280","name":"芳生野丙","lat":33.456666,"lng":133.041902}]}
